drb/drivers/discodata/__init__.py
drb/drivers/discodata/_version.py
drb/drivers/discodata/discodata.py
drb/topics/discodata/__init__.py
drb/topics/discodata/cortex.yml
drb_driver_discodata-1.4.1.dist-info/LICENCE.txt
drb_driver_discodata-1.4.1.dist-info/METADATA
drb_driver_discodata-1.4.1.dist-info/WHEEL
drb_driver_discodata-1.4.1.dist-info/entry_points.txt
drb_driver_discodata-1.4.1.dist-info/top_level.txt
drb_driver_discodata-1.4.1.dist-info/RECORD
