Metadata-Version: 2.1
Name: drb-driver-discodata
Version: 1.4.1
Summary: DRB DISCODATA Driver
Author: GAEL Systems
Author-email: drb-python@gael.fr
License: LGPLv3
Project-URL: Documentation, http://drb-python.gitlab.io/impl/discodata
Project-URL: Source, https://gitlab.com/drb-python/impl/discodata
Classifier: Programming Language :: Python :: 3.8
Classifier: Environment :: Plugins
Classifier: License :: OSI Approved :: GNU Lesser General Public License v3 (LGPLv3)
Requires-Python: >=3.8
License-File: LICENCE.txt
Requires-Dist: drb ~=2.2.0
Requires-Dist: drb-driver-http ~=1.3.1
Requires-Dist: drb-driver-json ~=1.3.0
Requires-Dist: pandas >=2.0.1
Requires-Dist: xarray >=2023.1.0
Requires-Dist: eccodes ~=1.5.2
